bluemax/__init__.py
bluemax/asyncpoolexecutor.py
bluemax/context.py
bluemax/main.py
bluemax/moo.py
bluemax/performer.py
bluemax/rpc.py
bluemax/settings.py
bluemax/aws/__init__.py
bluemax/aws/aws_broadcaster.py
bluemax/aws/aws_pubsub.py
bluemax/sa/__init__.py
bluemax/sa/db_session.py
bluemax/sa/serialize.py
bluemax/sa/tasks.py
bluemax/services/__init__.py
bluemax/services/server.py
bluemax/services/services_manager.py
bluemax/services/services_rpc.py
bluemax/tasks/__init__.py
bluemax/tasks/create.py
bluemax/tasks/run.py
bluemax/tasks/sidney.py
bluemax/tasks/stop.py
bluemax/tasks/utils.py
bluemax/utils/__init__.py
bluemax/utils/date_utils.py
bluemax/utils/describe.py
bluemax/utils/dot_dict.py
bluemax/utils/json_utils.py
bluemax/utils/proc_utils.py
bluemax/utils/status.py
bluemax/web/__init__.py
bluemax/web/auth_static_file_handler.py
bluemax/web/broadcaster.py
bluemax/web/rpc_websocket.py
bluemax/web/server.py
bluemax/web/authentication/__init__.py
bluemax/web/authentication/cognito_auth.py
bluemax/web/authentication/ldap_auth.py
bluemax/web/authentication/login_handler.py
bluemax/web/authentication/logout_handler.py
bluemax/web/authentication/ms_auth.py
bluemax/web/authentication/profile_handler.py
bluemax/web/authentication/user_mixin.py
bluemax/work/__init__.py
bluemax/work/rd_session.py
bluemax/work/redis_broadcaster.py
bluemax/work/redis_manger.py
bluemax/work/redis_pubsub.py
bluemax/work/worker.py
foo/__init__.py
foo/log.py
foo/procedures.py
foo/services.py
foo/settings.py
foo/urls.py
bluemax-0.2.7.dist-info/LICENSE
bluemax-0.2.7.dist-info/METADATA
bluemax-0.2.7.dist-info/WHEEL
bluemax-0.2.7.dist-info/entry_points.txt
bluemax-0.2.7.dist-info/top_level.txt
bluemax-0.2.7.dist-info/RECORD
