Metadata-Version: 2.1
Name: bluemax
Version: 0.2.7
Summary: UNKNOWN
Home-page: https://bitbucket.org/blueshed/bluemax/
License: UNKNOWN
Platform: UNKNOWN
Classifier: Programming Language :: Python :: 3
Classifier: License :: OSI Approved :: MIT License
Classifier: Operating System :: OS Independent
Requires-Dist: tornado
Requires-Dist: invoke
Requires-Dist: pyyaml
Provides-Extra: all
Requires-Dist: alembic ; extra == 'all'
Requires-Dist: aioredis ; extra == 'all'
Provides-Extra: dev
Requires-Dist: alembic ; extra == 'dev'
Requires-Dist: aioredis ; extra == 'dev'
Requires-Dist: wheel ; extra == 'dev'
Requires-Dist: twine ; extra == 'dev'
Requires-Dist: bumpversion ; extra == 'dev'
Requires-Dist: pytest-tornasync ; extra == 'dev'
Requires-Dist: pytest-cov ; extra == 'dev'
Requires-Dist: lovely-pytest-docker ; extra == 'dev'
Requires-Dist: pytest-benchmark ; extra == 'dev'
Requires-Dist: flake8 ; extra == 'dev'
Requires-Dist: ldap3 ; extra == 'dev'
Requires-Dist: ipython ; extra == 'dev'
Provides-Extra: redis
Requires-Dist: aioredis ; extra == 'redis'
Provides-Extra: sa
Requires-Dist: alembic ; extra == 'sa'
